fetch_url_package/__init__.py
fetch_url_package/cache.py
fetch_url_package/compat.py
fetch_url_package/extractor.py
fetch_url_package/fetch.py
fetch_url_package/text_encoder.py
fetch_url_package-1.6.0.dist-info/METADATA
fetch_url_package-1.6.0.dist-info/WHEEL
fetch_url_package-1.6.0.dist-info/top_level.txt
fetch_url_package-1.6.0.dist-info/RECORD
