Metadata-Version: 2.4
Name: fetch-url-package
Version: 1.6.0
Summary: Professional web content fetching and extraction toolkit with configurable extraction methods and domain caching
Author-email: FVG Team <team@fvg.com>
License: MIT
Project-URL: Homepage, https://github.com/SenseTime-FVG/fetch_url
Project-URL: Repository, https://github.com/SenseTime-FVG/fetch_url
Project-URL: Issues, https://github.com/SenseTime-FVG/fetch_url/issues
Keywords: web scraping,content extraction,html parser,web fetcher
Classifier: Development Status :: 4 - Beta
Classifier: Intended Audience :: Developers
Classifier: Programming Language :: Python :: 3.12
Classifier: Topic :: Internet :: WWW/HTTP
Classifier: Topic :: Software Development :: Libraries :: Python Modules
Requires-Python: >=3.8
Requires-Dist: httpx[http2]>=0.24.0
Requires-Dist: httpx[brotli]
Requires-Dist: lxml_html_clean
Provides-Extra: trafilatura
Requires-Dist: trafilatura>=1.6.0; extra == "trafilatura"
Provides-Extra: dev
Requires-Dist: pytest>=7.0.0; extra == "dev"
Requires-Dist: pytest-asyncio>=0.21.0; extra == "dev"
Requires-Dist: pytest-cov>=4.0.0; extra == "dev"
Requires-Dist: black>=23.0.0; extra == "dev"
Requires-Dist: flake8>=6.0.0; extra == "dev"
Requires-Dist: mypy>=1.0.0; extra == "dev"
Provides-Extra: all
Requires-Dist: trafilatura>=1.6.0; extra == "all"
